core_e2/__init__.py
core_e2/course.py
core_e2/utils.py
core_e2-0.1.0.dist-info/METADATA
core_e2-0.1.0.dist-info/WHEEL
core_e2-0.1.0.dist-info/top_level.txt
core_e2-0.1.0.dist-info/RECORD
