Metadata-Version: 2.4
Name: core_e2
Version: 0.1.0
Summary: Una practica de paquetes
Home-page: http://core_e2.com
Author: Alonzo Forgreting
Dynamic: author
Dynamic: description
Dynamic: description-content-type
Dynamic: home-page
Dynamic: summary
